hw/ShiftRegister.v
`ifndef SHIFT_REGISTER
`define SHIFT_REGISTER

module ShiftRegister
#(
  parameter nbits=8
)(
  input  logic             clk,
  input  logic             rst,
  input  logic             en,
  input  logic             shift_in,
  input  logic [nbits-1:0] seed,
  output logic [nbits-1:0] q
);

  always_ff @(posedge clk) begin
    if(rst)
      q <= seed;
    else if(en) begin
      for(int i = 0; i < nbits-1; i++)
        q[i] <= q[i+1];
      q[nbits-1] <= shift_in;
    end
    else
      q <= q;
  end

endmodule

`endif

hw/LFSR.v
`ifndef LINEAR_FEEDBACK_SHIFT_REGISTER
`define LINEAR_FEEDBACK_SHIFT_REGISTER

`include "ShiftRegister.v"

module LFSR
#(
  parameter nbits=8
)(
  input  logic             clk,
  input  logic             rst,
  input  logic             en,
  input  logic [nbits-1:0] tap,
  input  logic [nbits-1:0] seed,
  output logic             out
);

  logic             shift_in;
  logic [nbits-1:0] shift_reg_q;

  ShiftRegister shift_reg (
    .clk(clk),
    .rst(rst),
    .en(en),
    .shift_in(shift_in),
    .seed(seed),
    .q(shift_reg_q)
  );

  always_comb begin
    shift_in = shift_reg_q[0];
    for(int i = 1; i < nbits; i++) begin
      if(tap[i])
        shift_in = shift_in ^ shift_reg_q[i];
    end
  end

  assign out = shift_reg_q[0];

endmodule

`endif

test/waves.vcd
$date
	Thu Feb  6 17:13:53 2025
$end

$version
	Synopsys VCS version V-2023.12-SP2-1_Full64
$end

$timescale
	1ps
$end

$comment Csum: 1 6909c6ecb47d1b6f $end


$scope module LFSR $end
$var reg 1 ! clk $end
$var reg 1 " rst $end
$var reg 1 # en $end
$var reg 8 $ tap [7:0] $end
$var reg 8 % seed [7:0] $end
$var reg 1 & out $end
$var reg 1 ' shift_in $end
$var reg 8 ( shift_reg_q [7:0] $end

$scope begin unnamed$$_0 $end
$upscope $end


$scope module shift_reg $end
$var reg 1 ) clk $end
$var reg 1 * rst $end
$var reg 1 + en $end
$var reg 1 , shift_in $end
$var reg 8 - seed [7:0] $end
$var reg 8 . q [7:0] $end

$scope begin unnamed$$_0 $end
$upscope $end

$upscope $end

$upscope $end

$enddefinitions $end

#0
$dumpvars
x'
0+
1*
x,
bxxxxxxxx .
b00010000 %
b00010000 -
bxxxxxxxx (
b00000000 $
0!
0)
x&
1"
0#
$end
#5000
1!
1)
0"
0*
1#
1+
b11010000 $
b00010000 .
b00010000 (
0&
1'
1,
#10000
0!
0)
#15000
1!
1)
b10000000 $
0'
0,
b10001000 .
b10001000 (
1'
1,
#20000
0!
0)
#25000
1!
1)
b11100011 $
b11000100 .
b11000100 (
0'
0,
#30000
0!
0)
#35000
1!
1)
b11001111 $
1'
1,
b01100010 .
b01100010 (
0'
0,
#40000
0!
0)
#45000
1!
1)
b01000111 $
b00110001 .
b00110001 (
1&
1'
1,
#50000
0!
0)
#55000
1!
1)
b00100001 $
0'
0,
b10011000 .
b10011000 (
0&
#60000
0!
0)
#65000
1!
1)
b10111101 $
1'
1,
b01001100 .
b01001100 (
0'
0,
#70000
0!
0)
#75000
1!
1)
b11010100 $
b00100110 .
b00100110 (
1'
1,
#80000
0!
0)
#85000
1!
1)
b10010100 $
b10010011 .
b10010011 (
1&
#90000
0!
0)
#95000
1!
1)
b10101101 $
0'
0,
b11001001 .
b11001001 (
1'
1,
#100000
0!
0)
#105000
1!
1)
b11100000 $
b11100100 .
b11100100 (
0&
#110000
0!
0)
#115000
1!
1)
b00111001 $
b11110010 .
b11110010 (
0'
0,
#120000
0!
0)
#125000
1!
1)
b10100001 $
b01111001 .
b01111001 (
1&
#130000
0!
0)
#135000
1!
1)
b01100111 $
1'
1,
b00111100 .
b00111100 (
0&
0'
0,
#140000
0!
0)
#145000
1!
1)
b01110011 $
b00011110 .
b00011110 (
#150000
0!
0)
#155000
1!
1)
b00001011 $
b00001111 .
b00001111 (
1&
1'
1,
#160000
0!
0)
#165000
1!
1)
b11111110 $
0'
0,
b10000111 .
b10000111 (
#170000
0!
0)
#175000
1!
1)
b00101011 $
b01000011 .
b01000011 (
#180000
0!
0)
#185000
1!
1)
b11110000 $
b00100001 .
b00100001 (
#190000
0!
0)
#195000
1!
1)
b01101101 $
b00010000 .
b00010000 (
0&
#200000
0!
0)
#205000
1!
1)
b01000000 $
b00001000 .
b00001000 (
#210000
0!
0)
#215000
1!
1)
b10000100 $
b00000100 .
b00000100 (
1'
1,
#220000
0!
0)
#225000
1!
1)
b10010111 $
b10000010 .
b10000010 (
0'
0,
#230000
0!
0)
#235000
1!
1)
b01001001 $
b01000001 .
b01000001 (
1&
#240000
0!
0)
#245000
1!
1)
b01110000 $
b00100000 .
b00100000 (
0&
1'
1,
#250000
0!
0)
#255000
1!
1)
b01000100 $
0'
0,
b10010000 .
b10010000 (
#260000
0!
0)
#265000
1!
1)
b01111010 $
1'
1,
b01001000 .
b01001000 (
0'
0,
#270000
0!
0)
#275000
1!
1)
b11001011 $
b00100100 .
b00100100 (
#280000
0!
0)
#285000
1!
1)
b11100101 $
b00010010 .
b00010010 (
#290000
0!
0)
#295000
1!
1)
b11110010 $
b00001001 .
b00001001 (
1&
1'
1,
#300000
0!
0)
#305000
1!
1)
b01001000 $
0'
0,
b10000100 .
b10000100 (
0&
#310000
0!
0)
#315000
1!
1)
b11001000 $
1'
1,
b01000010 .
b01000010 (
#320000
0!
0)
#325000
1!
1)
b00101000 $
0'
0,
b10100001 .
b10100001 (
1&
#330000
0!
0)
#335000
1!
1)
b10111001 $
1'
1,
b01010000 .
b01010000 (
0&
#340000
0!
0)
#345000
1!
1)
b00011010 $
b10101000 .
b10101000 (
#350000
0!
0)
#355000
1!
1)
b01111101 $
0'
0,
b11010100 .
b11010100 (
1'
1,
#360000
0!
0)
#365000
1!
1)
b10110001 $
0'
0,
b11101010 .
b11101010 (
#370000
0!
0)
#375000
1!
1)
b11010100 $
b01110101 .
b01110101 (
1&
#380000
0!
0)
#385000
1!
1)
b01100111 $
b00111010 .
b00111010 (
0&
#390000
0!
0)
#395000
1!
1)
b10101100 $
b00011101 .
b00011101 (
1&
1'
1,
#400000
0!
0)
#405000
1!
1)
b10010000 $
0'
0,
b10001110 .
b10001110 (
0&
1'
1,
#410000
0!
0)
#415000
1!
1)
b10000100 $
0'
0,
b11000111 .
b11000111 (
1&
1'
1,
#420000
0!
0)
#425000
1!
1)
b11100111 $
b11100011 .
b11100011 (
#430000
0!
0)
#435000
1!
1)
b01000111 $
b11110001 .
b11110001 (
0'
0,
#440000
0!
0)
#445000
1!
1)
b11000111 $
1'
1,
b01111000 .
b01111000 (
0&
#450000
0!
0)
#455000
1!
1)
b10100011 $
b10111100 .
b10111100 (
0'
0,
#460000
0!
0)
#465000
1!
1)
b00110100 $
1'
1,
b01011110 .
b01011110 (
0'
0,
#470000
0!
0)
#475000
1!
1)
b11111111 $
1'
1,
b00101111 .
b00101111 (
1&
#480000
0!
0)
#485000
1!
1)
b10001100 $
b10010111 .
b10010111 (
#490000
0!
0)
#495000
1!
1)
b01010100 $
b11001011 .
b11001011 (
0'
0,
#500000
0!
0)
#505000
1!
1)
b00110101 $
1'
1,
b01100101 .
b01100101 (
#510000
0!
0)
#515000
1!
1)
b01011111 $
b10110010 .
b10110010 (
0&
0'
0,
#520000
0!
0)
#525000
1!
1)
b01000100 $
b01011001 .
b01011001 (
1&
#530000
0!
0)
#535000
1!
1)
b11110100 $
1'
1,
b00101100 .
b00101100 (
0&
0'
0,
#540000
0!
0)
#545000
1!
1)
b00110100 $
b00010110 .
b00010110 (
#550000
0!
0)
#555000
1!
1)
b11101101 $
1'
1,
b00001011 .
b00001011 (
1&
0'
0,
#560000
0!
0)
#565000
1!
1)
b10001100 $
b00000101 .
b00000101 (
#570000
0!
0)
#575000
1!
1)
b01010010 $
1'
1,
b00000010 .
b00000010 (
0&
#580000
0!
0)
#585000
1!
1)
b11000100 $
0'
0,
b10000001 .
b10000001 (
1&
#590000
0!
0)
#595000
1!
1)
b00100101 $
1'
1,
b01000000 .
b01000000 (
0&
0'
0,
#600000
0!
0)
#605000
1!
1)
b00000100 $
b00100000 .
b00100000 (
#610000
0!
0)
#615000
1!
1)
b10101011 $
1'
1,
b00010000 .
b00010000 (
0'
0,
#620000
0!
0)
#625000
1!
1)
b10010001 $
1'
1,
b00001000 .
b00001000 (
0'
0,
#630000
0!
0)
#635000
1!
1)
b10100111 $
b00000100 .
b00000100 (
1'
1,
#640000
0!
0)
#645000
1!
1)
b11100000 $
0'
0,
b10000010 .
b10000010 (
1'
1,
#650000
0!
0)
#655000
1!
1)
b00010100 $
0'
0,
b11000001 .
b11000001 (
1&
1'
1,
#660000
0!
0)
#665000
1!
1)
b11100000 .
b11100000 (
0&
0'
0,
#670000
0!
0)
#675000
1!
1)
b01011101 $
1'
1,
b01110000 .
b01110000 (
0'
0,
#680000
0!
0)
#685000
1!
1)
b01101010 $
b00111000 .
b00111000 (
#690000
0!
0)
#695000
1!
1)
b01101110 $
b00011100 .
b00011100 (
#700000
0!
0)
#705000
1!
1)
b11001010 $
1'
1,
b00001110 .
b00001110 (
0'
0,
#710000
0!
0)
#715000
1!
1)
b11100100 $
1'
1,
b00000111 .
b00000111 (
1&
0'
0,
#720000
0!
0)
#725000
1!
1)
b11001001 $
1'
1,
b00000011 .
b00000011 (
#730000
0!
0)
#735000
1!
1)
b11100011 $
0'
0,
b10000001 .
b10000001 (
#740000
0!
0)
#745000
1!
1)
b01100000 $
1'
1,
b01000000 .
b01000000 (
0&
#750000
0!
0)
#755000
1!
1)
b11101001 $
b10100000 .
b10100000 (
0'
0,
#760000
0!
0)
#765000
1!
1)
b00111010 $
1'
1,
b01010000 .
b01010000 (
#770000
0!
0)
#775000
1!
1)
b01110101 $
0'
0,
b10101000 .
b10101000 (
1'
1,
#780000
0!
0)
#785000
1!
1)
b11000100 $
b11010100 .
b11010100 (
#790000
0!
0)
#795000
1!
1)
b10101000 $
b11101010 .
b11101010 (
#800000
0!
0)
#805000
1!
1)
b01101111 $
0'
0,
b11110101 .
b11110101 (
1&
#810000
0!
0)
#815000
1!
1)
b01000110 $
1'
1,
b01111010 .
b01111010 (
0&
0'
0,
#820000
0!
0)
#825000
1!
1)
b11101101 $
1'
1,
b00111101 .
b00111101 (
1&
0'
0,
#830000
0!
0)
#835000
1!
1)
b11011110 $
b00011110 .
b00011110 (
0&
#840000
0!
0)
#845000
1!
1)
b10011011 $
1'
1,
b00001111 .
b00001111 (
1&
#850000
0!
0)
#855000
1!
1)
b11110100 $
0'
0,
b10000111 .
b10000111 (
1'
1,
#860000
0!
0)
#865000
1!
1)
b01011111 $
b11000011 .
b11000011 (
#870000
0!
0)
#875000
1!
1)
b10101010 $
b11100001 .
b11100001 (
#880000
0!
0)
#885000
1!
1)
b00110011 $
0'
0,
b11110000 .
b11110000 (
0&
#890000
0!
0)
#895000
1!
1)
b11110100 $
b01111000 .
b01111000 (
1'
1,
#900000
0!
0)
#905000
1!
1)
b01011101 $
b10111100 .
b10111100 (
#910000
0!
0)
#915000
1!
1)
b01010011 $
b11011110 .
b11011110 (
#920000
0!
0)
#925000
1!
1)
b00101101 $
0'
0,
b11101111 .
b11101111 (
1&
#930000
0!
0)
#935000
1!
1)
b01011000 $
1'
1,
b01110111 .
b01110111 (
#940000
0!
0)
#945000
1!
1)
b00100011 $
b10111011 .
b10111011 (
#950000
0!
0)
#955000
1!
1)
b00100101 $
0'
0,
b11011101 .
b11011101 (
#960000
0!
0)
#965000
1!
1)
b11110110 $
1'
1,
b01101110 .
b01101110 (
0&
0'
0,
#970000
0!
0)
#975000
1!
1)
b10111001 $
b00110111 .
b00110111 (
1&
1'
1,
#980000
0!
0)
#985000
1!
1)
b10011100 $
b10011011 .
b10011011 (
0'
0,
#990000
0!
0)
#995000
1!
1)
b00010101 $
b01001101 .
b01001101 (
#1000000
0!
0)
#1005000
1!
1)
b00010111 $
b00100110 .
b00100110 (
0&
#1010000
0!
0)
#1015000
1!
1)
b00110100 $
b00010011 .
b00010011 (
1&
#1020000
0!
0)
#1025000
1!
1)
b10010010 $
1'
1,
b00001001 .
b00001001 (
#1030000
0!
0)
#1035000
1!
1)
b00111100 $
0'
0,
b10000100 .
b10000100 (
0&
1'
1,
#1040000
0!
0)
#1045000
1!
1)
b01001010 $
0'
0,
b11000010 .
b11000010 (
#1050000
0!
0)
#1055000
1!
1)
b00111011 $
1'
1,
b01100001 .
b01100001 (
1&
0'
0,
#1060000
0!
0)
#1065000
1!
1)
b00011100 $
1'
1,
b00110000 .
b00110000 (
0&
#1070000
0!
0)
#1075000
1!
1)
b10111011 $
0'
0,
b10011000 .
b10011000 (
1'
1,
#1080000
0!
0)
#1085000
1!
1)
b10000011 $
b11001100 .
b11001100 (
#1090000
0!
0)
#1095000
1!
1)
b01001101 $
b11100110 .
b11100110 (
0'
0,
#1100000
0!
0)
#1105000
1!
1)
b10100110 $
b01110011 .
b01110011 (
1&
1'
1,
#1110000
0!
0)
#1115000
1!
1)
b01110010 $
b10111001 .
b10111001 (
#1120000
0!
0)
#1125000
1!
1)
b11110111 $
0'
0,
b11011100 .
b11011100 (
0&
#1130000
0!
0)
#1135000
1!
1)
b01111010 $
1'
1,
b01101110 .
b01101110 (
0'
0,
#1140000
0!
0)
#1145000
1!
1)
b00010100 $
1'
1,
b00110111 .
b00110111 (
1&
#1150000
0!
0)
#1155000
1!
1)
b01111101 $
0'
0,
b10011011 .
b10011011 (
1'
1,
#1160000
0!
0)
#1165000
1!
1)
b01010111 $
b11001101 .
b11001101 (
#1170000
0!
0)
#1175000
1!
1)
b11101110 $
b11100110 .
b11100110 (
0&
#1180000
0!
0)
#1185000
1!
1)
b00011101 $
b11110011 .
b11110011 (
1&
0'
0,
#1190000
0!
0)
#1195000
1!
1)
b10111111 $
1'
1,
b01111001 .
b01111001 (
0'
0,
#1200000
0!
0)
#1205000
1!
1)
b00101000 $
1'
1,
b00111100 .
b00111100 (
0&
0'
0,
#1210000
0!
0)
#1215000
1!
1)
b11100111 $
b00011110 .
b00011110 (
#1220000
0!
0)
#1225000
1!
1)
b10001111 $
1'
1,
b00001111 .
b00001111 (
1&
0'
0,
#1230000
0!
0)
#1235000
1!
1)
b00000010 $
b00000111 .
b00000111 (
#1240000
0!
0)
#1245000
1!
1)
b10011110 $
1'
1,
b00000011 .
b00000011 (
0'
0,
#1250000
0!
0)
#1255000
1!
1)
b00010101 $
1'
1,
b00000001 .
b00000001 (
#1260000
0!
0)
#1265000
1!
1)
b01010110 $
b10000000 .
b10000000 (
0&
0'
0,
#1270000
0!
0)
#1275000
1!
1)
b10011010 $
1'
1,
b01000000 .
b01000000 (
0'
0,
#1280000
0!
0)
#1285000
1!
1)
b11011100 $
1'
1,
b00100000 .
b00100000 (
0'
0,
#1290000
0!
0)
#1295000
1!
1)
b01101011 $
1'
1,
b00010000 .
b00010000 (
0'
0,
#1300000
0!
0)
#1305000
1!
1)
b00011111 $
1'
1,
b00001000 .
b00001000 (
#1310000
0!
0)
#1315000
1!
1)
b11100000 $
0'
0,
b10000100 .
b10000100 (
1'
1,
#1320000
0!
0)
#1325000
1!
1)
b10000101 $
0'
0,
b11000010 .
b11000010 (
1'
1,
#1330000
0!
0)
#1335000
1!
1)
b11011010 $
b11100001 .
b11100001 (
1&
#1340000
0!
0)
#1345000
1!
1)
b10010000 $
0'
0,
b11110000 .
b11110000 (
0&
#1350000
0!
0)
#1355000
1!
1)
b11011011 $
1'
1,
b01111000 .
b01111000 (
#1360000
0!
0)
#1365000
1!
1)
b10011001 $
0'
0,
b10111100 .
b10111100 (
1'
1,
#1370000
0!
0)
#1375000
1!
1)
b10110001 $
b11011110 .
b11011110 (
0'
0,
#1380000
0!
0)
#1385000
1!
1)
b00100111 $
b01101111 .
b01101111 (
1&
#1390000
0!
0)
#1395000
1!
1)
b00111001 $
1'
1,
b00110111 .
b00110111 (
#1400000
0!
0)
#1405000
1!
1)
b01101110 $
0'
0,
b10011011 .
b10011011 (
1'
1,
#1410000
0!
0)
#1415000
1!
1)
b00111101 $
b11001101 .
b11001101 (
#1420000
0!
0)
#1425000
1!
1)
b01011001 $
b11100110 .
b11100110 (
0&
#1430000
0!
0)
#1435000
1!
1)
b01000000 $
b11110011 .
b11110011 (
1&
0'
0,
#1440000
0!
0)
#1445000
1!
1)
b10100011 $
b01111001 .
b01111001 (
#1450000
0!
0)
#1455000
1!
1)
b11010100 $
1'
1,
b00111100 .
b00111100 (
0&
0'
0,
#1460000
0!
0)
#1465000
1!
1)
b11010001 $
1'
1,
b00011110 .
b00011110 (
#1470000
0!
0)
#1475000
1!
1)
b01110011 $
0'
0,
b10001111 .
b10001111 (
1&
#1480000
0!
0)
#1485000
1!
1)
b01001010 $
1'
1,
b01000111 .
b01000111 (
#1490000
0!
0)
#1495000
1!
1)
b00011001 $
b10100011 .
b10100011 (
#1500000
0!
0)
#1505000
1!
1)
b10110111 $
0'
0,
b11010001 .
b11010001 (
1'
1,
#1510000
0!
0)
#1515000
1!
1)
b01000100 $
0'
0,
b11101000 .
b11101000 (
0&
1'
1,
#1520000
0!
0)
#1525000
1!
1)
b00001011 $
b11110100 .
b11110100 (
0'
0,
#1530000
0!
0)
#1535000
1!
1)
b10100000 $
b01111010 .
b01111010 (
1'
1,
#1540000
0!
0)
#1545000
1!
1)
b00111010 $
0'
0,
b10111101 .
b10111101 (
1&
#1550000
0!
0)
#1555000
1!
1)
b01000010 $
1'
1,
b01011110 .
b01011110 (
0&
0'
0,
#1560000
0!
0)
#1565000
1!
1)
b01111101 $
b00101111 .
b00101111 (
1&
#1570000
0!
0)
#1575000
1!
1)
b11100101 $
1'
1,
b00010111 .
b00010111 (
0'
0,
#1580000
0!
0)
#1585000
1!
1)
b00001111 $
1'
1,
b00001011 .
b00001011 (
#1590000
0!
0)
#1595000
1!
1)
b10000001 $
b10000101 .
b10000101 (
0'
0,
#1600000
0!
0)
#1605000
1!
1)
b00000110 $
b01000010 .
b01000010 (
0&
1'
1,
#1610000
0!
0)
#1615000
1!
1)
b01110111 $
0'
0,
b10100001 .
b10100001 (
1&
#1620000
0!
0)
#1625000
1!
1)
b10100010 $
1'
1,
b01010000 .
b01010000 (
0&
0'
0,
#1630000
0!
0)
#1635000
1!
1)
b01000110 $
1'
1,
b00101000 .
b00101000 (
0'
0,
#1640000
0!
0)
#1645000
1!
1)
b01010111 $
b00010100 .
b00010100 (
#1650000
0!
0)
#1655000
1!
1)
b10010011 $
1'
1,
b00001010 .
b00001010 (
#1660000
0!
0)
#1665000
1!
1)
b00011110 $
0'
0,
b10000101 .
b10000101 (
1&
#1670000
0!
0)
#1675000
1!
1)
b00101101 $
b01000010 .
b01000010 (
0&
#1680000
0!
0)
#1685000
1!
1)
b00001110 $
1'
1,
b00100001 .
b00100001 (
1&
#1690000
0!
0)
#1695000
1!
1)
b01010111 $
b10010000 .
b10010000 (
0&
#1700000
0!
0)
#1705000
1!
1)
b00111001 $
b11001000 .
b11001000 (
#1710000
0!
0)
#1715000
1!
1)
b11110100 $
0'
0,
b11100100 .
b11100100 (
#1720000
0!
0)
#1725000
1!
1)
b01011010 $
1'
1,
b01110010 .
b01110010 (
#1730000
0!
0)
#1735000
1!
1)
b11001011 $
0'
0,
b10111001 .
b10111001 (
1&
1'
1,
#1740000
0!
0)
#1745000
1!
1)
b10000110 $
0'
0,
b11011100 .
b11011100 (
0&
#1750000
0!
0)
#1755000
1!
1)
b11101000 $
1'
1,
b01101110 .
b01101110 (
#1760000
0!
0)
#1765000
1!
1)
b00000010 $
b10110111 .
b10110111 (
1&
0'
0,
#1770000
0!
0)
#1775000
1!
1)
b00011111 $
b01011011 .
b01011011 (
#1780000
0!
0)
#1785000
1!
1)
b00001111 $
1'
1,
b00101101 .
b00101101 (
#1790000
0!
0)
#1795000
1!
1)
b01101100 $
0'
0,
b10010110 .
b10010110 (
0&
1'
1,
#1800000
0!
0)
#1805000
1!
1)
b01110111 $
b11001011 .
b11001011 (
1&
#1810000
0!
0)
#1815000
1!
1)
b00011101 $
0'
0,
b11100101 .
b11100101 (
#1820000
0!
0)
#1825000
1!
1)
b01001000 $
b01110010 .
b01110010 (
0&
1'
1,
#1830000
0!
0)
#1835000
1!
1)
b01011011 $
b10111001 .
b10111001 (
1&
#1840000
0!
0)
#1845000
1!
1)
b10001011 $
b11011100 .
b11011100 (
0&
0'
0,
#1850000
0!
0)
#1855000
1!
1)
b10011000 $
1'
1,
b01101110 .
b01101110 (
#1860000
0!
0)
#1865000
1!
1)
b11101010 $
0'
0,
b10110111 .
b10110111 (
1&
#1870000
0!
0)
#1875000
1!
1)
b00001011 $
b01011011 .
b01011011 (
1'
1,
#1880000
0!
0)
#1885000
1!
1)
b11000000 $
0'
0,
b10101101 .
b10101101 (
#1890000
0!
0)
#1895000
1!
1)
b01010000 $
1'
1,
b01010110 .
b01010110 (
0&
0'
0,
#1900000
0!
0)
#1905000
1!
1)
b11101100 $
b00101011 .
b00101011 (
1&
1'
1,
#1910000
0!
0)
#1915000
1!
1)
b10010011 $
0'
0,
b10010101 .
b10010101 (
1'
1,
#1920000
0!
0)
#1925000
1!
1)
b01011010 $
0'
0,
b11001010 .
b11001010 (
0&
1'
1,
#1930000
0!
0)
#1935000
1!
1)
b00110110 $
b11100101 .
b11100101 (
1&
#1940000
0!
0)
#1945000
1!
1)
b01011110 $
b11110010 .
b11110010 (
0&
#1950000
0!
0)
#1955000
1!
1)
b01100100 $
0'
0,
b11111001 .
b11111001 (
1&
1'
1,
#1960000
0!
0)
#1965000
1!
1)
b01100001 $
b11111100 .
b11111100 (
0&
0'
0,
#1970000
0!
0)
#1975000
1!
1)
b00010010 $
1'
1,
b01111110 .
b01111110 (
0'
0,
#1980000
0!
0)
#1985000
1!
1)
b00010100 $
b00111111 .
b00111111 (
1&
1'
1,
#1990000
0!
0)
#1995000
1!
1)
b11101011 $
0'
0,
b10011111 .
b10011111 (
#2000000
0!
0)
#2005000
1!
1)
b10110101 $
b01001111 .
b01001111 (
#2010000
0!
0)
#2015000
1!
1)
b10100111 $
1'
1,
b00100111 .
b00100111 (
0'
0,
#2020000
0!
0)
#2025000
1!
1)
b11100110 $
b00010011 .
b00010011 (
#2030000
0!
0)
#2035000
1!
1)
b10010110 $
1'
1,
b00001001 .
b00001001 (
#2040000
0!
0)
#2045000
1!
1)
b10011000 $
0'
0,
b10000100 .
b10000100 (
0&
1'
1,
#2050000
0!
0)
#2055000
1!
1)
b00010111 $
b11000010 .
b11000010 (
#2060000
0!
0)
#2065000
1!
1)
b00100001 $
0'
0,
b11100001 .
b11100001 (
1&
#2070000
0!
0)
#2075000
1!
1)
b10100010 $
1'
1,
b01110000 .
b01110000 (
0&
#2080000
0!
0)
#2085000
1!
1)
b11000000 $
b10111000 .
b10111000 (
#2090000
0!
0)
#2095000
1!
1)
b11110011 $
b11011100 .
b11011100 (
#2100000
0!
0)
#2105000
1!
1)
b11101110 $
0'
0,
b11101110 .
b11101110 (
#2110000
0!
0)
#2115000
1!
1)
b11010111 $
b01110111 .
b01110111 (
1&
1'
1,
#2120000
0!
0)
#2125000
1!
1)
b10000010 $
0'
0,
b10111011 .
b10111011 (
1'
1,
#2130000
0!
0)
#2135000
1!
1)
b01110110 $
0'
0,
b11011101 .
b11011101 (
#2140000
0!
0)
#2145000
1!
1)
b11001101 $
1'
1,
b01101110 .
b01101110 (
0&
#2150000
0!
0)
#2155000
1!
1)
b11110011 $
b10110111 .
b10110111 (
1&
#2160000
0!
0)
#2165000
1!
1)
b00010000 $
0'
0,
b11011011 .
b11011011 (
#2170000
0!
0)
#2175000
1!
1)
b10110100 $
1'
1,
b01101101 .
b01101101 (
#2180000
0!
0)
#2185000
1!
1)
b01111100 $
b10110110 .
b10110110 (
0&
#2190000
0!
0)
#2195000
1!
1)
b00000100 $
b11011011 .
b11011011 (
1&
#2200000
0!
0)
#2205000
1!
1)
b11010101 $
0'
0,
b11101101 .
b11101101 (
#2210000
0!
0)
#2215000
1!
1)
b00000110 $
b01110110 .
b01110110 (
0&
#2220000
0!
0)
#2225000
1!
1)
b11010001 $
b00111011 .
b00111011 (
1&
#2230000
0!
0)
#2235000
1!
1)
b11010101 $
b00011101 .
b00011101 (
1'
1,
#2240000
0!
0)
#2245000
1!
1)
b11000001 $
b10001110 .
b10001110 (
0&
#2250000
0!
0)
#2255000
1!
1)
b00001111 $
b11000111 .
b11000111 (
1&
#2260000
0!
0)
#2265000
1!
1)
b01100110 $
0'
0,
b11100011 .
b11100011 (
#2270000
0!
0)
#2275000
1!
1)
b00101101 $
b01110001 .
b01110001 (
#2280000
0!
0)
#2285000
1!
1)
b00100100 $
b00111000 .
b00111000 (
0&
1'
1,
#2290000
0!
0)
#2295000
1!
1)
b01010000 $
b10011100 .
b10011100 (
#2300000
0!
0)
#2305000
1!
1)
b00100010 $
0'
0,
b11001110 .
b11001110 (
1'
1,
#2310000
0!
0)
#2315000
1!
1)
b00100100 $
b11100111 .
b11100111 (
1&
#2320000
0!
0)
#2325000
1!
1)
b11011100 $
0'
0,
b11110011 .
b11110011 (
#2330000
0!
0)
#2335000
1!
1)
b11001110 $
b01111001 .
b01111001 (
1'
1,
#2340000
0!
0)
#2345000
1!
1)
b00101101 $
b10111100 .
b10111100 (
0&
#2350000
0!
0)
#2355000
1!
1)
b01011101 $
b11011110 .
b11011110 (
0'
0,
#2360000
0!
0)
#2365000
1!
1)
b00101011 $
b01101111 .
b01101111 (
1&
#2370000
0!
0)
#2375000
1!
1)
b00011010 $
1'
1,
b00110111 .
b00110111 (
#2380000
0!
0)
#2385000
1!
1)
b10111100 $
0'
0,
b10011011 .
b10011011 (
#2390000
0!
0)
#2395000
1!
1)
b00111010 $
b01001101 .
b01001101 (
#2400000
0!
0)
#2405000
1!
1)
b11011001 $
1'
1,
b00100110 .
b00100110 (
0&
0'
0,
#2410000
0!
0)
#2415000
1!
1)
b01001100 $
1'
1,
b00010011 .
b00010011 (
1&
#2420000
0!
0)
#2425000
1!
1)
b11110000 $
0'
0,
b10001001 .
b10001001 (
#2430000
0!
0)
#2435000
1!
1)
b00010110 $
1'
1,
b01000100 .
b01000100 (
0&
#2440000
0!
0)
#2445000
1!
1)
b01111001 $
b10100010 .
b10100010 (
#2450000
0!
0)
#2455000
1!
1)
b01101000 $
b11010001 .
b11010001 (
1&
0'
0,
#2460000
0!
0)
#2465000
1!
1)
b00010001 $
b01101000 .
b01101000 (
0&
#2470000
0!
0)
#2475000
1!
1)
b11110001 $
b00110100 .
b00110100 (
#2480000
0!
0)
#2485000
1!
1)
b01000001 $
b00011010 .
b00011010 (
#2490000
0!
0)
#2495000
1!
1)
b01011001 $
b00001101 .
b00001101 (
1&
#2500000
0!
0)
#2505000
1!
1)
b00101110 $
1'
1,
b00000110 .
b00000110 (
0&
0'
0,
#2510000
0!
0)
#2515000
1!
1)
b00110101 $
1'
1,
b00000011 .
b00000011 (
1&
#2520000
0!
0)
#2525000
1!
1)
b00000001 $
b10000001 .
b10000001 (
#2530000
0!
0)
#2535000
1!
1)
b00110011 $
b11000000 .
b11000000 (
0&
0'
0,
#2540000
0!
0)
#2545000
1!
1)
b01111111 $
1'
1,
b01100000 .
b01100000 (
0'
0,
#2550000
0!
0)
#2555000
1!
1)
b11001001 $
1'
1,
b00110000 .
b00110000 (
0'
0,
#2560000
0!
0)
#2565000
1!
1)
b11011000 $
1'
1,
b00011000 .
b00011000 (
0'
0,
#2570000
0!
0)
#2575000
1!
1)
b01011011 $
b00001100 .
b00001100 (
1'
1,
#2580000
0!
0)
#2585000
1!
1)
b10101101 $
0'
0,
b10000110 .
b10000110 (
#2590000
0!
0)
#2595000
1!
1)
b10110100 $
b01000011 .
b01000011 (
1&
1'
1,
#2600000
0!
0)
#2605000
1!
1)
b11010011 $
b10100001 .
b10100001 (
0'
0,
#2610000
0!
0)
#2615000
1!
1)
b10001011 $
b01010000 .
b01010000 (
0&
#2620000
0!
0)
#2625000
1!
1)
b01010101 $
b00101000 .
b00101000 (
#2630000
0!
0)
#2635000
1!
1)
b11010001 $
b00010100 .
b00010100 (
1'
1,
#2640000
0!
0)
#2645000
1!
1)
b00110100 $
0'
0,
b10001010 .
b10001010 (
#2650000
0!
0)
#2655000
1!
1)
b01111110 $
b01000101 .
b01000101 (
1&
1'
1,
#2660000
0!
0)
#2665000
1!
1)
b01010000 $
0'
0,
b10100010 .
b10100010 (
0&
#2670000
0!
0)
#2675000
1!
1)
b00100101 $
1'
1,
b01010001 .
b01010001 (
1&
#2680000
0!
0)
#2685000
1!
1)
b00100001 $
b10101000 .
b10101000 (
0&
#2690000
0!
0)
#2695000
1!
1)
b00100111 $
b11010100 .
b11010100 (
#2700000
0!
0)
#2705000
1!
1)
b00111000 $
b11101010 .
b11101010 (
0'
0,
#2710000
0!
0)
#2715000
1!
1)
b00000110 $
1'
1,
b01110101 .
b01110101 (
1&
0'
0,
#2720000
0!
0)
#2725000
1!
1)
b10110101 $
b00111010 .
b00111010 (
0&
#2730000
0!
0)
#2735000
1!
1)
b10011000 $
b00011101 .
b00011101 (
1&
1'
1,
#2740000
0!
0)
#2745000
1!
1)
b10011101 $
0'
0,
b10001110 .
b10001110 (
0&
1'
1,
#2750000
0!
0)
#2755000
1!
1)
b10111100 $
b11000111 .
b11000111 (
1&
#2760000
0!
0)
#2765000
1!
1)
b01111110 $
0'
0,
b11100011 .
b11100011 (
#2770000
0!
0)
#2775000
1!
1)
b00001100 $
1'
1,
b01110001 .
b01110001 (
#2780000
0!
0)
#2785000
1!
1)
b01011100 $
b10111000 .
b10111000 (
0&
0'
0,
#2790000
0!
0)
#2795000
1!
1)
b11110111 $
1'
1,
b01011100 .
b01011100 (
#2800000
0!
0)
#2805000
1!
1)
b01010111 $
b10101110 .
b10101110 (
0'
0,
