hw/ShiftRegister.v
`ifndef SHIFT_REGISTER
`define SHIFT_REGISTER

module ShiftRegister#(
  parameter nbits=8
)(
  (* keep=1 *) input  logic             clk,
  (* keep=1 *) input  logic             rst,
  (* keep=1 *) input  logic             en,
  (* keep=1 *) input  logic             shift_in,
  (* keep=1 *) input  logic [nbits-1:0] seed,
  (* keep=1 *) output logic [nbits-1:0] q
);

  always_ff @(posedge clk) begin
    if(rst)
      q <= seed;
    else if(en) begin
      for(int i = 0; i < nbits-1; i++)
        q[i] <= q[i+1];
      q[nbits-1] <= shift_in;
    end
    else
      q <= q;
  end

endmodule

`endif

hw/LFSR.v
`ifndef LINEAR_FEEDBACK_SHIFT_REGISTER
`define LINEAR_FEEDBACK_SHIFT_REGISTER

`include "ShiftRegister.v"

module LFSR
#(
  parameter nbits=8
)(
  input  logic             clk,
  input  logic             rst,
  input  logic             en,
  input  logic [nbits-1:0] tap,
  input  logic [nbits-1:0] seed,
  output logic             out
);

  logic             shift_in;
  logic [nbits-1:0] shift_reg_q;

  ShiftRegister shift_reg
  (
    .clk      (clk),
    .rst      (rst),
    .en       (en),
    .shift_in (shift_in),
    .seed     (seed),
    .q        (shift_reg_q)
  );

  always_comb begin
    shift_in = shift_reg_q[0];
    for(int i = 1; i < nbits; i++) begin
      if(tap[i])
        shift_in = shift_in ^ shift_reg_q[i];
    end
  end

  assign out = shift_reg_q[0];

endmodule

`endif

hw/RandomEngineDpath.v
`ifndef RANDOM_ENGINE_DPATH
`define RANDOM_ENGINE_DPATH

`include "LFSR.v"

module RandomEngineDpath
(
  input  logic       clk,
  input  logic       rst,

  // I/O Interface

  input  logic [7:0] tap,
  input  logic [7:0] seed,
  output logic       out,

  // Control Signals

  input  logic       lfsr_en
);

  logic lfsr_out;

  LFSR lfsr
  (
    .clk  (clk),
    .rst  (rst),
    .en   (lfsr_en),
    .tap  (tap),
    .seed (seed),
    .out  (lfsr_out)
  );

  assign out = lfsr_out;

endmodule

`endif

hw/Register.v
`ifndef REGISTER
`define REGISTER

module Register
#(
  parameter nbits=8
)(
  input  logic             clk,
  input  logic             rst,
  input  logic             en,
  input  logic [nbits-1:0] d,
  output logic [nbits-1:0] q
);

  always_ff @(posedge clk) begin
    if(rst)
      q <= {nbits{1'b0}};
    else
      q <= (en ? d : q);
  end

endmodule

`endif

hw/RandomEngineCtrl.v
`ifndef RANDOM_ENGINE_CTRL
`define RANDOM_ENGINE_CTRL

`include "Register.v"

module RandomEngineCtrl
(
  input  logic clk,
  input  logic rst,

  // I/O Interface

  input  logic start,
  input  logic stop,
  output logic active,

  // Control Signal
  
  output logic lfsr_en
);

  // State Encodings

  localparam STATE_WAIT = 1'b0;
  localparam STATE_LFSR = 1'b1;

  // State Register

  logic state;
  logic state_next;

  Register#(1) state_reg
  (
    .clk (clk),
    .rst (rst),
    .en  (1'b1),
    .d   (state_next),
    .q   (state)
  );

  // State Transition Logic

  always_comb begin
    case(state)
      STATE_WAIT: state_next = (start ? STATE_LFSR : STATE_WAIT);
      STATE_LFSR: state_next = (stop  ? STATE_WAIT : STATE_LFSR);
    endcase
  end

  // Output Logic

  always_comb begin
    case(state)
      STATE_WAIT: begin
        active  = 0;
        lfsr_en = start;
      end
      STATE_LFSR: begin
        active  = 1;
        lfsr_en = ~stop;
      end
    endcase
  end

endmodule

`endif

hw/RandomEngine.v
`ifndef RANDOM_ENGINE
`define RANDOM_ENGINE

`include "RandomEngineCtrl.v"
`include "RandomEngineDpath.v"

module RandomEngine
(
  (* keep=1 *) input  logic       clk,
  (* keep=1 *) input  logic       rst,
  (* keep=1 *) input  logic       start,
  (* keep=1 *) input  logic       stop,
  (* keep=1 *) input  logic [7:0] tap,
  (* keep=1 *) input  logic [7:0] seed,
  (* keep=1 *) output logic       active,
  (* keep=1 *) output logic       out
);

  logic lfsr_en;

  RandomEngineCtrl ctrl
  (
    .*
  );

  RandomEngineDpath dpath
  (
    .*
  );

endmodule

`endif

test/waves.vcd
$date
	Sun Feb  9 13:19:30 2025
$end

$version
	Synopsys VCS version V-2023.12-SP2-1_Full64
$end

$timescale
	1ps
$end

$comment Csum: 1 69490e8d7617adae $end


$scope module RandomEngine $end
$var reg 1 ! clk $end
$var reg 1 " rst $end
$var reg 1 # start $end
$var reg 1 $ stop $end
$var reg 8 % tap [7:0] $end
$var reg 8 & seed [7:0] $end
$var reg 1 ' active $end
$var reg 1 ( out $end
$var reg 1 ) lfsr_en $end

$scope module ctrl $end
$var reg 1 * clk $end
$var reg 1 + rst $end
$var reg 1 , start $end
$var reg 1 - stop $end
$var reg 1 . active $end
$var reg 1 / lfsr_en $end
$var reg 1 0 state $end
$var reg 1 1 state_next $end

$scope module state_reg $end
$var reg 1 2 clk $end
$var reg 1 3 rst $end
$var reg 1 4 en $end
$var reg 1 5 d [0:0] $end
$var reg 1 6 q [0:0] $end
$upscope $end

$upscope $end


$scope module dpath $end
$var reg 1 7 clk $end
$var reg 1 8 rst $end
$var reg 8 9 tap [7:0] $end
$var reg 8 : seed [7:0] $end
$var reg 1 ; out $end
$var reg 1 < lfsr_en $end
$var reg 1 = lfsr_out $end

$scope module lfsr $end
$var reg 1 > clk $end
$var reg 1 ? rst $end
$var reg 1 @ en $end
$var reg 8 A tap [7:0] $end
$var reg 8 B seed [7:0] $end
$var reg 1 C out $end
$var reg 1 D shift_in $end
$var reg 8 E shift_reg_q [7:0] $end

$scope begin unnamed$$_0 $end
$upscope $end


$scope module shift_reg $end
$var reg 1 F clk $end
$var reg 1 G rst $end
$var reg 1 H en $end
$var reg 1 I shift_in $end
$var reg 8 J seed [7:0] $end
$var reg 8 K q [7:0] $end

$scope begin unnamed$$_0 $end
$upscope $end

$upscope $end

$upscope $end

$upscope $end

$upscope $end

$enddefinitions $end

#0
$dumpvars
x.
x/
1+
0,
0-
x5
x@
x<
18
14
1?
x)
x6
xD
xH
1G
xI
x0
x1
13
bxxxxxxxx K
b10011101 :
b00000000 9
b10011101 B
b00000000 A
b10011101 &
b10011101 J
bxxxxxxxx E
b00000000 %
xC
x=
x;
x(
0!
0*
07
02
0>
0F
x'
1"
0#
0$
$end
#500
1!
1*
17
12
1>
1F
0"
08
0?
0G
0+
03
1#
1,
1$
1-
b00111001 %
b00111001 9
b00111001 A
b10000001 &
b10000001 :
b10000001 B
b10000001 J
06
00
b10011101 K
b10011101 E
1C
1=
1;
1(
11
15
1/
1)
1<
1@
1H
0.
0'
1D
1I
#1000
0!
0*
07
02
0>
0F
#1500
1!
1*
17
12
1>
1F
b00001111 %
b00001111 9
b00001111 A
b11101100 &
b11101100 :
b11101100 B
b11101100 J
16
10
b11001110 K
b11001110 E
0C
0=
0;
0(
01
05
0/
0)
0<
0@
0H
1.
1'
#2000
0!
0*
07
02
0>
0F
#2500
1!
1*
17
12
1>
1F
0#
0,
0$
0-
b00011111 %
b00011111 9
b00011111 A
b11000100 &
b11000100 :
b11000100 B
b11000100 J
11
15
1/
1)
1<
1@
1H
06
00
01
05
0/
0)
0<
0@
0H
0.
0'
#3000
0!
0*
07
02
0>
0F
#3500
1!
1*
17
12
1>
1F
1"
18
1?
1G
1+
13
1#
1,
b00011100 %
b00011100 9
b00011100 A
b10001100 &
b10001100 :
b10001100 B
b10001100 J
11
15
1/
1)
1<
1@
1H
0D
0I
#4000
0!
0*
07
02
0>
0F
#4500
1!
1*
17
12
1>
1F
0"
08
0?
0G
0+
03
b11100100 %
b11100100 9
b11100100 A
b01111000 &
b01111000 :
b01111000 B
b01111000 J
1D
1I
b10001100 K
b10001100 E
0D
0I
#5000
0!
0*
07
02
0>
0F
#5500
1!
1*
17
12
1>
1F
b01101111 %
b01101111 9
b01101111 A
b00010011 &
b00010011 :
b00010011 B
b00010011 J
16
10
b01000110 K
b01000110 E
1.
1'
1D
1I
#6000
0!
0*
07
02
0>
0F
#6500
1!
1*
17
12
1>
1F
1"
18
1?
1G
1+
13
b11111010 %
b11111010 9
b11111010 A
b11000111 &
b11000111 :
b11000111 B
b11000111 J
0D
0I
b10100011 K
b10100011 E
1C
1=
1;
1(
#7000
0!
0*
07
02
0>
0F
#7500
1!
1*
17
12
1>
1F
0"
08
0?
0G
0+
03
1$
1-
b10101101 %
b10101101 9
b10101101 A
b00001110 &
b00001110 :
b00001110 B
b00001110 J
01
05
0/
0)
0<
0@
0H
1D
1I
06
00
b11000111 K
b11000111 E
11
15
1/
1)
1<
1@
1H
0.
0'
#8000
0!
0*
07
02
0>
0F
#8500
1!
1*
17
12
1>
1F
0$
0-
b10101111 %
b10101111 9
b10101111 A
b00100100 &
b00100100 :
b00100100 B
b00100100 J
0D
0I
16
10
b11100011 K
b11100011 E
1.
1'
#9000
0!
0*
07
02
0>
0F
#9500
1!
1*
17
12
1>
1F
1"
18
1?
1G
1+
13
1$
1-
b01111100 %
b01111100 9
b01111100 A
b11100111 &
b11100111 :
b11100111 B
b11100111 J
01
05
0/
0)
0<
0@
0H
1D
1I
b01110001 K
b01110001 E
0D
0I
#10000
0!
0*
07
02
0>
0F
#10500
1!
1*
17
12
1>
1F
0"
08
0?
0G
0+
03
0#
0,
b01001100 %
b01001100 9
b01001100 A
b00001010 &
b00001010 :
b00001010 B
b00001010 J
06
00
b11100111 K
b11100111 E
0.
0'
1D
1I
#11000
0!
0*
07
02
0>
0F
#11500
1!
1*
17
12
1>
1F
1"
18
1?
1G
1+
13
1#
1,
b00111011 %
b00111011 9
b00111011 A
b11101011 &
b11101011 :
b11101011 B
b11101011 J
11
15
1/
1)
1<
1@
1H
#12000
0!
0*
07
02
0>
0F
#12500
1!
1*
17
12
1>
1F
0"
08
0?
0G
0+
03
0#
0,
b00010111 %
b00010111 9
b00010111 A
b00001101 &
b00001101 :
b00001101 B
b00001101 J
01
05
0/
0)
0<
0@
0H
b11101011 K
b11101011 E
0D
0I
#13000
0!
0*
07
02
0>
0F
#13500
1!
1*
17
12
1>
1F
1"
18
1?
1G
1+
13
1#
1,
0$
0-
b01001011 %
b01001011 9
b01001011 A
b10010000 &
b10010000 :
b10010000 B
b10010000 J
11
15
1/
1)
1<
1@
1H
#14000
0!
0*
07
02
0>
0F
#14500
1!
1*
17
12
1>
1F
0"
08
0?
0G
0+
03
b11001101 %
b11001101 9
b11001101 A
b00000110 &
b00000110 :
b00000110 B
b00000110 J
b10010000 K
b10010000 E
0C
0=
0;
0(
1D
1I
#15000
0!
0*
07
02
0>
0F
#15500
1!
1*
17
12
1>
1F
1"
18
1?
1G
1+
13
0#
0,
b00010001 %
b00010001 9
b00010001 A
b11000101 &
b11000101 :
b11000101 B
b11000101 J
01
05
0/
0)
0<
0@
0H
16
10
b11001000 K
b11001000 E
11
15
1/
1)
1<
1@
1H
1.
1'
0D
0I
#16000
0!
0*
07
02
0>
0F
#16500
1!
1*
17
12
1>
1F
0"
08
0?
0G
0+
03
b11000101 %
b11000101 9
b11000101 A
b10100100 &
b10100100 :
b10100100 B
b10100100 J
06
00
b11000101 K
b11000101 E
1C
1=
1;
1(
01
05
0/
0)
0<
0@
0H
0.
0'
#17000
0!
0*
07
02
0>
0F
#17500
1!
1*
17
12
1>
1F
b01010011 %
b01010011 9
b01010011 A
b01110110 &
b01110110 :
b01110110 B
b01110110 J
#18000
0!
0*
07
02
0>
0F
#18500
1!
1*
17
12
1>
1F
1#
1,
b11111011 %
b11111011 9
b11111011 A
b01001010 &
b01001010 :
b01001010 B
b01001010 J
11
15
1/
1)
1<
1@
1H
1D
1I
#19000
0!
0*
07
02
0>
0F
#19500
1!
1*
17
12
1>
1F
1$
1-
b00000010 %
b00000010 9
b00000010 A
b11111000 &
b11111000 :
b11111000 B
b11111000 J
16
10
b11100010 K
b11100010 E
0C
0=
0;
0(
01
05
0/
0)
0<
0@
0H
1.
1'
#20000
0!
0*
07
02
0>
0F
#20500
1!
1*
17
12
1>
1F
0$
0-
b01110001 %
b01110001 9
b01110001 A
b01011001 &
b01011001 :
b01011001 B
b01011001 J
11
15
1/
1)
1<
1@
1H
0D
0I
06
00
0.
0'
#21000
0!
0*
07
02
0>
0F
#21500
1!
1*
17
12
1>
1F
1"
18
1?
1G
1+
13
b11101010 %
b11101010 9
b11101010 A
b10100101 &
b10100101 :
b10100101 B
b10100101 J
16
10
b01110001 K
b01110001 E
1C
1=
1;
1(
1.
1'
1D
1I
#22000
0!
0*
07
02
0>
0F
#22500
1!
1*
17
12
1>
1F
0"
08
0?
0G
0+
03
0#
0,
b00001101 %
b00001101 9
b00001101 A
b01010011 &
b01010011 :
b01010011 B
b01010011 J
06
00
b10100101 K
b10100101 E
01
05
0/
0)
0<
0@
0H
0.
0'
0D
0I
#23000
0!
0*
07
02
0>
0F
#23500
1!
1*
17
12
1>
1F
1$
1-
b00000011 %
b00000011 9
b00000011 A
b11100101 &
b11100101 :
b11100101 B
b11100101 J
1D
1I
#24000
0!
0*
07
02
0>
0F
#24500
1!
1*
17
12
1>
1F
0$
0-
b01100100 %
b01100100 9
b01100100 A
b11101111 &
b11101111 :
b11101111 B
b11101111 J
#25000
0!
0*
07
02
0>
0F
#25500
1!
1*
17
12
1>
1F
1"
18
1?
1G
1+
13
1#
1,
b11100100 %
b11100100 9
b11100100 A
b00001101 &
b00001101 :
b00001101 B
b00001101 J
11
15
1/
1)
1<
1@
1H
0D
0I
#26000
0!
0*
07
02
0>
0F
#26500
1!
1*
17
12
1>
1F
b00111100 %
b00111100 9
b00111100 A
b11010110 &
b11010110 :
b11010110 B
b11010110 J
1D
1I
b00001101 K
b00001101 E
#27000
0!
0*
07
02
0>
0F
#27500
1!
1*
17
12
1>
1F
0#
0,
1$
1-
b01101010 %
b01101010 9
b01101010 A
01
05
0/
0)
0<
0@
0H
0D
0I
b11010110 K
b11010110 E
0C
0=
0;
0(
#28000
0!
0*
07
02
0>
0F
#28500
1!
1*
17
12
1>
1F
0"
08
0?
0G
0+
03
b10100001 %
b10100001 9
b10100001 A
b00110100 &
b00110100 :
b00110100 B
b00110100 J
1D
1I
#29000
0!
0*
07
02
0>
0F
#29500
1!
1*
17
12
1>
1F
0$
0-
b00010111 %
b00010111 9
b00010111 A
b10011111 &
b10011111 :
b10011111 B
b10011111 J
#30000
0!
0*
07
02
0>
0F
#30500
1!
1*
17
12
1>
1F
1"
18
1?
1G
1+
13
1$
1-
b01101111 %
b01101111 9
b01101111 A
b11011001 &
b11011001 :
b11011001 B
b11011001 J
#31000
0!
0*
07
02
0>
0F
#31500
1!
1*
17
12
1>
1F
0"
08
0?
0G
0+
03
b10010100 %
b10010100 9
b10010100 A
b10010110 &
b10010110 :
b10010110 B
b10010110 J
b11011001 K
b11011001 E
1C
1=
1;
1(
#32000
0!
0*
07
02
0>
0F
#32500
1!
1*
17
12
1>
1F
1#
1,
b10000011 %
b10000011 9
b10000011 A
b10100100 &
b10100100 :
b10100100 B
b10100100 J
11
15
1/
1)
1<
1@
1H
0D
0I
#33000
0!
0*
07
02
0>
0F
#33500
1!
1*
17
12
1>
1F
b10111001 %
b10111001 9
b10111001 A
b10110000 &
b10110000 :
b10110000 B
b10110000 J
16
10
b01101100 K
b01101100 E
0C
0=
0;
0(
01
05
0/
0)
0<
0@
0H
1.
1'
#34000
0!
0*
07
02
0>
0F
#34500
1!
1*
17
12
1>
1F
0#
0,
0$
0-
b10001111 %
b10001111 9
b10001111 A
b01111101 &
b01111101 :
b01111101 B
b01111101 J
11
15
1/
1)
1<
1@
1H
06
00
01
05
0/
0)
0<
0@
0H
0.
0'
#35000
0!
0*
07
02
0>
0F
#35500
1!
1*
17
12
1>
1F
1"
18
1?
1G
1+
13
1#
1,
b10000101 %
b10000101 9
b10000101 A
b00000001 &
b00000001 :
b00000001 B
b00000001 J
11
15
1/
1)
1<
1@
1H
1D
1I
#36000
0!
0*
07
02
0>
0F
#36500
1!
1*
17
12
1>
1F
0"
08
0?
0G
0+
03
0#
0,
1$
1-
b00110111 %
b00110111 9
b00110111 A
b10101010 &
b10101010 :
b10101010 B
b10101010 J
01
05
0/
0)
0<
0@
0H
0D
0I
b00000001 K
b00000001 E
1C
1=
1;
1(
1D
1I
#37000
0!
0*
07
02
0>
0F
#37500
1!
1*
17
12
1>
1F
1"
18
1?
1G
1+
13
b00111001 %
b00111001 9
b00111001 A
b00001101 &
b00001101 :
b00001101 B
b00001101 J
#38000
0!
0*
07
02
0>
0F
#38500
1!
1*
17
12
1>
1F
0"
08
0?
0G
0+
03
1#
1,
0$
0-
b00101111 %
b00101111 9
b00101111 A
b11001011 &
b11001011 :
b11001011 B
b11001011 J
11
15
1/
1)
1<
1@
1H
b00001101 K
b00001101 E
#39000
0!
0*
07
02
0>
0F
#39500
1!
1*
17
12
1>
1F
1"
18
1?
1G
1+
13
0#
0,
b10110101 %
b10110101 9
b10110101 A
b11011110 &
b11011110 :
b11011110 B
b11011110 J
01
05
0/
0)
0<
0@
0H
0D
0I
16
10
b10000110 K
b10000110 E
0C
0=
0;
0(
11
15
1/
1)
1<
1@
1H
1.
1'
#40000
0!
0*
07
02
0>
0F
#40500
1!
1*
17
12
1>
1F
0"
08
0?
0G
0+
03
1#
1,
b01111011 %
b01111011 9
b01111011 A
b11001010 &
b11001010 :
b11001010 B
b11001010 J
1D
1I
06
00
b11011110 K
b11011110 E
0.
0'
0D
0I
#41000
0!
0*
07
02
0>
0F
#41500
1!
1*
17
12
1>
1F
1"
18
1?
1G
1+
13
b11100011 %
b11100011 9
b11100011 A
b10010011 &
b10010011 :
b10010011 B
b10010011 J
1D
1I
16
10
b01101111 K
b01101111 E
1C
1=
1;
1(
1.
1'
0D
0I
#42000
0!
0*
07
02
0>
0F
#42500
1!
1*
17
12
1>
1F
1$
1-
b01101001 %
b01101001 9
b01101001 A
b11011111 &
b11011111 :
b11011111 B
b11011111 J
01
05
0/
0)
0<
0@
0H
06
00
b10010011 K
b10010011 E
11
15
1/
1)
1<
1@
1H
0.
0'
1D
1I
#43000
0!
0*
07
02
0>
0F
#43500
1!
1*
17
12
1>
1F
0#
0,
0$
0-
b00100110 %
b00100110 9
b00100110 A
b11011110 &
b11011110 :
b11011110 B
b11011110 J
01
05
0/
0)
0<
0@
0H
0D
0I
b11011111 K
b11011111 E
1D
1I
#44000
0!
0*
07
02
0>
0F
#44500
1!
1*
17
12
1>
1F
1$
1-
b11111100 %
b11111100 9
b11111100 A
b00110110 &
b00110110 :
b00110110 B
b00110110 J
0D
0I
b11011110 K
b11011110 E
0C
0=
0;
0(
1D
1I
#45000
0!
0*
07
02
0>
0F
#45500
1!
1*
17
12
1>
1F
0"
08
0?
0G
0+
03
1#
1,
b01000101 %
b01000101 9
b01000101 A
b11100011 &
b11100011 :
b11100011 B
b11100011 J
11
15
1/
1)
1<
1@
1H
0D
0I
b00110110 K
b00110110 E
1D
1I
#46000
0!
0*
07
02
0>
0F
#46500
1!
1*
17
12
1>
1F
0#
0,
b00001000 %
b00001000 9
b00001000 A
b11100100 &
b11100100 :
b11100100 B
b11100100 J
01
05
0/
0)
0<
0@
0H
0D
0I
16
10
b10011011 K
b10011011 E
1C
1=
1;
1(
1.
1'
#47000
0!
0*
07
02
0>
0F
#47500
1!
1*
17
12
1>
1F
1"
18
1?
1G
1+
13
0$
0-
b11110111 %
b11110111 9
b11110111 A
b11111011 &
b11111011 :
b11111011 B
b11111011 J
11
15
1/
1)
1<
1@
1H
06
00
01
05
0/
0)
0<
0@
0H
0.
0'
#48000
0!
0*
07
02
0>
0F
#48500
1!
1*
17
12
1>
1F
0"
08
0?
0G
0+
03
1#
1,
b01001111 %
b01001111 9
b01001111 A
b00010010 &
b00010010 :
b00010010 B
b00010010 J
11
15
1/
1)
1<
1@
1H
1D
1I
b11111011 K
b11111011 E
0D
0I
#49000
0!
0*
07
02
0>
0F
#49500
1!
1*
17
12
1>
1F
1"
18
1?
1G
1+
13
1$
1-
b01100111 %
b01100111 9
b01100111 A
b10000000 &
b10000000 :
b10000000 B
b10000000 J
16
10
b01111101 K
b01111101 E
01
05
0/
0)
0<
0@
0H
1.
1'
#50000
0!
0*
07
02
0>
0F
#50500
1!
1*
17
12
1>
1F
0#
0,
b11111101 %
b11111101 9
b11111101 A
b11000101 &
b11000101 :
b11000101 B
b11000101 J
06
00
b10000000 K
b10000000 E
0C
0=
0;
0(
0.
0'
1D
1I
#51000
0!
0*
07
02
0>
0F
#51500
1!
1*
17
12
1>
1F
1#
1,
b00100111 %
b00100111 9
b00100111 A
b01000011 &
b01000011 :
b01000011 B
b01000011 J
11
15
1/
1)
1<
1@
1H
0D
0I
b11000101 K
b11000101 E
1C
1=
1;
1(
#52000
0!
0*
07
02
0>
0F
#52500
1!
1*
17
12
1>
1F
0"
08
0?
0G
0+
03
0#
0,
0$
0-
b11110010 %
b11110010 9
b11110010 A
b00101000 &
b00101000 :
b00101000 B
b00101000 J
01
05
0/
0)
0<
0@
0H
1D
1I
b01000011 K
b01000011 E
#53000
0!
0*
07
02
0>
0F
#53500
1!
1*
17
12
1>
1F
1#
1,
1$
1-
b01000101 %
b01000101 9
b01000101 A
b10000110 &
b10000110 :
b10000110 B
b10000110 J
11
15
1/
1)
1<
1@
1H
0D
0I
#54000
0!
0*
07
02
0>
0F
#54500
1!
1*
17
12
1>
1F
1"
18
1?
1G
1+
13
0#
0,
b00001111 %
b00001111 9
b00001111 A
b11101111 &
b11101111 :
b11101111 B
b11101111 J
01
05
0/
0)
0<
0@
0H
16
10
b00100001 K
b00100001 E
1.
1'
1D
1I
#55000
0!
0*
07
02
0>
0F
#55500
1!
1*
17
12
1>
1F
0"
08
0?
0G
0+
03
0$
0-
b01100101 %
b01100101 9
b01100101 A
b11001000 &
b11001000 :
b11001000 B
b11001000 J
11
15
1/
1)
1<
1@
1H
0D
0I
06
00
b11101111 K
b11101111 E
01
05
0/
0)
0<
0@
0H
0.
0'
#56000
0!
0*
07
02
0>
0F
#56500
1!
1*
17
12
1>
1F
1"
18
1?
1G
1+
13
1#
1,
b00111011 %
b00111011 9
b00111011 A
b00011011 &
b00011011 :
b00011011 B
b00011011 J
11
15
1/
1)
1<
1@
1H
#57000
0!
0*
07
02
0>
0F
#57500
1!
1*
17
12
1>
1F
0"
08
0?
0G
0+
03
1$
1-
b10011111 %
b10011111 9
b10011111 A
b11101101 &
b11101101 :
b11101101 B
b11101101 J
1D
1I
b00011011 K
b00011011 E
0D
0I
#58000
0!
0*
07
02
0>
0F
#58500
1!
1*
17
12
1>
1F
1"
18
1?
1G
1+
13
0#
0,
b11100110 %
b11100110 9
b11100110 A
b10011100 &
b10011100 :
b10011100 B
b10011100 J
01
05
0/
0)
0<
0@
0H
16
10
b00001101 K
b00001101 E
1.
1'
#59000
0!
0*
07
02
0>
0F
#59500
1!
1*
17
12
1>
1F
0$
0-
b11011000 %
b11011000 9
b11011000 A
b11000000 &
b11000000 :
b11000000 B
b11000000 J
11
15
1/
1)
1<
1@
1H
06
00
b10011100 K
b10011100 E
0C
0=
0;
0(
01
05
0/
0)
0<
0@
0H
0.
0'
1D
1I
#60000
0!
0*
07
02
0>
0F
#60500
1!
1*
17
12
1>
1F
0"
08
0?
0G
0+
03
1#
1,
b10100110 %
b10100110 9
b10100110 A
b11011101 &
b11011101 :
b11011101 B
b11011101 J
11
15
1/
1)
1<
1@
1H
0D
0I
b11000000 K
b11000000 E
1D
1I
#61000
0!
0*
07
02
0>
0F
#61500
1!
1*
17
12
1>
1F
1"
18
1?
1G
1+
13
0#
0,
b01101010 %
b01101010 9
b01101010 A
b11011000 &
b11011000 :
b11011000 B
b11011000 J
01
05
0/
0)
0<
0@
0H
16
10
b11100000 K
b11100000 E
11
15
1/
1)
1<
1@
1H
1.
1'
0D
0I
#62000
0!
0*
07
02
0>
0F
#62500
1!
1*
17
12
1>
1F
0"
08
0?
0G
0+
03
1#
1,
1$
1-
b10011101 %
b10011101 9
b10011101 A
b10001001 &
b10001001 :
b10001001 B
b10001001 J
01
05
0/
0)
0<
0@
0H
1D
1I
06
00
b11011000 K
b11011000 E
11
15
1/
1)
1<
1@
1H
0.
0'
#63000
0!
0*
07
02
0>
0F
#63500
1!
1*
17
12
1>
1F
0#
0,
b10011000 %
b10011000 9
b10011000 A
b10101011 &
b10101011 :
b10101011 B
b10101011 J
01
05
0/
0)
0<
0@
0H
16
10
b11101100 K
b11101100 E
1.
1'
0D
0I
#64000
0!
0*
07
02
0>
0F
#64500
1!
1*
17
12
1>
1F
b11101010 %
b11101010 9
b11101010 A
b01101100 &
b01101100 :
b01101100 B
b01101100 J
06
00
0.
0'
#65000
0!
0*
07
02
0>
0F
#65500
1!
1*
17
12
1>
1F
1"
18
1?
1G
1+
13
b00110100 %
b00110100 9
b00110100 A
b00011001 &
b00011001 :
b00011001 B
b00011001 J
#66000
0!
0*
07
02
0>
0F
#66500
1!
1*
17
12
1>
1F
0"
08
0?
0G
0+
03
0$
0-
b10000111 %
b10000111 9
b10000111 A
b01111010 &
b01111010 :
b01111010 B
b01111010 J
b00011001 K
b00011001 E
1C
1=
1;
1(
1D
1I
#67000
0!
0*
07
02
0>
0F
#67500
1!
1*
17
12
1>
1F
b01110101 %
b01110101 9
b01110101 A
b01011100 &
b01011100 :
b01011100 B
b01011100 J
0D
0I
#68000
0!
0*
07
02
0>
0F
#68500
1!
1*
17
12
1>
1F
1$
1-
b10011100 %
b10011100 9
b10011100 A
b11101000 &
b11101000 :
b11101000 B
b11101000 J
1D
1I
#69000
0!
0*
07
02
0>
0F
#69500
1!
1*
17
12
1>
1F
1"
18
1?
1G
1+
13
0$
0-
b11100000 %
b11100000 9
b11100000 A
b00010001 &
b00010001 :
b00010001 B
b00010001 J
#70000
0!
0*
07
02
0>
0F
#70500
1!
1*
17
12
1>
1F
1$
1-
b00011111 %
b00011111 9
b00011111 A
b00110000 &
b00110000 :
b00110000 B
b00110000 J
b00010001 K
b00010001 E
0D
0I
#71000
0!
0*
07
02
0>
0F
#71500
1!
1*
17
12
1>
1F
0"
08
0?
0G
0+
03
0$
0-
b11101111 %
b11101111 9
b11101111 A
b01011110 &
b01011110 :
b01011110 B
b01011110 J
1D
1I
b00110000 K
b00110000 E
0C
0=
0;
0(
#72000
0!
0*
07
02
0>
0F
#72500
1!
1*
17
12
1>
1F
1#
1,
1$
1-
b11111110 %
b11111110 9
b11111110 A
b10010010 &
b10010010 :
b10010010 B
b10010010 J
11
15
1/
1)
1<
1@
1H
0D
0I
#73000
0!
0*
07
02
0>
0F
#73500
1!
1*
17
12
1>
1F
1"
18
1?
1G
1+
13
0$
0-
b01111001 %
b01111001 9
b01111001 A
b00100011 &
b00100011 :
b00100011 B
b00100011 J
16
10
b00011000 K
b00011000 E
1.
1'
#74000
0!
0*
07
02
0>
0F
#74500
1!
1*
17
12
1>
1F
0"
08
0?
0G
0+
03
0#
0,
1$
1-
b00011100 %
b00011100 9
b00011100 A
b10101111 &
b10101111 :
b10101111 B
b10101111 J
01
05
0/
0)
0<
0@
0H
06
00
b00100011 K
b00100011 E
1C
1=
1;
1(
0.
0'
1D
1I
#75000
0!
0*
07
02
0>
0F
#75500
1!
1*
17
12
1>
1F
1"
18
1?
1G
1+
13
0$
0-
b11111010 %
b11111010 9
b11111010 A
b10000100 &
b10000100 :
b10000100 B
b10000100 J
#76000
0!
0*
07
02
0>
0F
#76500
1!
1*
17
12
1>
1F
1$
1-
b01100111 %
b01100111 9
b01100111 A
b01010010 &
b01010010 :
b01010010 B
b01010010 J
b10000100 K
b10000100 E
0C
0=
0;
0(
#77000
0!
0*
07
02
0>
0F
#77500
1!
1*
17
12
1>
1F
0"
08
0?
0G
0+
03
1#
1,
b11100010 %
b11100010 9
b11100010 A
b11111011 &
b11111011 :
b11111011 B
b11111011 J
11
15
1/
1)
1<
1@
1H
b01010010 K
b01010010 E
0D
0I
#78000
0!
0*
07
02
0>
0F
#78500
1!
1*
17
12
1>
1F
0$
0-
b11010001 %
b11010001 9
b11010001 A
b10000111 &
b10000111 :
b10000111 B
b10000111 J
16
10
b00101001 K
b00101001 E
1C
1=
1;
1(
1.
1'
1D
1I
#79000
0!
0*
07
02
0>
0F
#79500
1!
1*
17
12
1>
1F
0#
0,
1$
1-
b10111100 %
b10111100 9
b10111100 A
b11000100 &
b11000100 :
b11000100 B
b11000100 J
01
05
0/
0)
0<
0@
0H
b10010100 K
b10010100 E
0C
0=
0;
0(
#80000
0!
0*
07
02
0>
0F
#80500
1!
1*
17
12
1>
1F
0$
0-
b00001111 %
b00001111 9
b00001111 A
b10000100 &
b10000100 :
b10000100 B
b10000100 J
11
15
1/
1)
1<
1@
1H
06
00
01
05
0/
0)
0<
0@
0H
0.
0'
#81000
0!
0*
07
02
0>
0F
#81500
1!
1*
17
12
1>
1F
1#
1,
b01110010 %
b01110010 9
b01110010 A
b01001111 &
b01001111 :
b01001111 B
b01001111 J
11
15
1/
1)
1<
1@
1H
#82000
0!
0*
07
02
0>
0F
#82500
1!
1*
17
12
1>
1F
0#
0,
b11100101 %
b11100101 9
b11100101 A
b10000110 &
b10000110 :
b10000110 B
b10000110 J
01
05
0/
0)
0<
0@
0H
0D
0I
16
10
b11001010 K
b11001010 E
11
15
1/
1)
1<
1@
1H
1.
1'
#83000
0!
0*
07
02
0>
0F
#83500
1!
1*
17
12
1>
1F
1"
18
1?
1G
1+
13
1#
1,
1$
1-
b10000001 %
b10000001 9
b10000001 A
b01011101 &
b01011101 :
b01011101 B
b01011101 J
01
05
0/
0)
0<
0@
0H
1D
1I
b01100101 K
b01100101 E
1C
1=
1;
1(
#84000
0!
0*
07
02
0>
0F
#84500
1!
1*
17
12
1>
1F
0$
0-
b01101101 %
b01101101 9
b01101101 A
b00010110 &
b00010110 :
b00010110 B
b00010110 J
11
15
1/
1)
1<
1@
1H
0D
0I
06
00
b01011101 K
b01011101 E
0.
0'
#85000
0!
0*
07
02
0>
0F
